[{"Land": "\ufeffArgentina", "Log_Population": "17.50", "Points": "1603", "WCQuali": "17", "Continent": "South America", "WCTitles": "2"}, {"Land": "Brazil", "Log_Population": "19.05", "Points": "1672", "WCQuali": "21", "Continent": "South America", "WCTitles": "5"}, {"Land": "Chile", "Log_Population": "16.60", "Points": "1411", "WCQuali": "9", "Continent": "South America", "WCTitles": "0"}, {"Land": "Germany", "Log_Population": "18.23", "Points": "1464", "WCQuali": "19", "Continent": "Europe", "WCTitles": "4"}, {"Land": "Belgium", "Log_Population": "16.16", "Points": "1281", "WCQuali": "13", "Continent": "Europe", "WCTitles": "0"}, {"Land": "Portugal", "Log_Population": "16.18", "Points": "1259", "WCQuali": "7", "Continent": "Europe", "WCTitles": "0"}, {"Land": "Colombia", "Log_Population": "17.59", "Points": "1348", "WCQuali": "6", "Continent": "South America", "WCTitles": "0"}, {"Land": "Switzerland", "Log_Population": "15.83", "Points": "1212", "WCQuali": "11", "Continent": "Europe", "WCTitles": "0"}, {"Land": "Wales", "Log_Population": "14.88", "Points": "1119", "WCQuali": "1", "Continent": "Europe", "WCTitles": "0"}, {"Land": "Uruguay", "Log_Population": "15.05", "Points": "1097", "WCQuali": "13", "Continent": "South America", "WCTitles": "2"}, {"Land": "France", "Log_Population": "17.92", "Points": "1294", "WCQuali": "15", "Continent": "Europe", "WCTitles": "1"}, {"Land": "Iceland", "Log_Population": "12.62", "Points": "872", "WCQuali": "1", "Continent": "Europe", "WCTitles": "0"}, {"Land": "Spain", "Log_Population": "17.51", "Points": "1204", "WCQuali": "15", "Continent": "Europe", "WCTitles": "1"}, {"Land": "Poland", "Log_Population": "17.47", "Points": "1183", "WCQuali": "8", "Continent": "Europe", "WCTitles": "0"}, {"Land": "Croatia", "Log_Population": "15.32", "Points": "1016", "WCQuali": "5", "Continent": "Europe", "WCTitles": "0"}, {"Land": "Italy", "Log_Population": "17.88", "Points": "1165", "WCQuali": "18", "Continent": "Europe", "WCTitles": "4"}, {"Land": "England", "Log_Population": "17.74", "Points": "1103", "WCQuali": "15", "Continent": "Europe", "WCTitles": "1"}, {"Land": "Peru", "Log_Population": "17.16", "Points": "1044", "WCQuali": "5", "Continent": "South America", "WCTitles": "0"}, {"Land": "Costa Rica", "Log_Population": "15.22", "Points": "902", "WCQuali": "5", "Continent": "Latin/North America", "WCTitles": "0"}, {"Land": "Mexico", "Log_Population": "18.49", "Points": "1076", "WCQuali": "16", "Continent": "Latin/North America", "WCTitles": "0"}, {"Land": "Northern Ireland", "Log_Population": "14.35", "Points": "823", "WCQuali": "3", "Continent": "Europe", "WCTitles": "0"}, {"Land": "Slovakia", "Log_Population": "15.51", "Points": "846", "WCQuali": "1", "Continent": "Europe", "WCTitles": "0"}, {"Land": "Republic of Ireland", "Log_Population": "15.22", "Points": "823", "WCQuali": "3", "Continent": "Europe", "WCTitles": "0"}, {"Land": "Bosnia and Herzegovina", "Log_Population": "15.32", "Points": "815", "WCQuali": "1", "Continent": "Europe", "WCTitles": "0"}, {"Land": "Ecuador", "Log_Population": "16.42", "Points": "839", "WCQuali": "3", "Continent": "South America", "WCTitles": "0"}, {"Land": "Egypt", "Log_Population": "18.18", "Points": "910", "WCQuali": "3", "Continent": "Africa", "WCTitles": "0"}, {"Land": "Hungary", "Log_Population": "16.12", "Points": "801", "WCQuali": "9", "Continent": "Europe", "WCTitles": "0"}, {"Land": "Senegal", "Log_Population": "16.30", "Points": "805", "WCQuali": "2", "Continent": "Africa", "WCTitles": "0"}, {"Land": "Sweden", "Log_Population": "16.01", "Points": "768", "WCQuali": "12", "Continent": "Europe", "WCTitles": "0"}, {"Land": "Austria", "Log_Population": "15.92", "Points": "762", "WCQuali": "7", "Continent": "Europe", "WCTitles": "0"}, {"Land": "Turkey", "Log_Population": "18.07", "Points": "863", "WCQuali": "2", "Continent": "Europe", "WCTitles": "0"}, {"Land": "Netherlands", "Log_Population": "16.62", "Points": "792", "WCQuali": "10", "Continent": "Europe", "WCTitles": "0"}, {"Land": "Paraguay", "Log_Population": "15.69", "Points": "738", "WCQuali": "8", "Continent": "South America", "WCTitles": "0"}, {"Land": "Cameroon", "Log_Population": "16.67", "Points": "779", "WCQuali": "7", "Continent": "Africa", "WCTitles": "0"}, {"Land": "Burkina Faso", "Log_Population": "16.40", "Points": "765", "WCQuali": "0", "Continent": "Africa", "WCTitles": "0"}, {"Land": "Iran", "Log_Population": "18.05", "Points": "820", "WCQuali": "5", "Continent": "Asia", "WCTitles": "0"}, {"Land": "Greece", "Log_Population": "16.18", "Points": "730", "WCQuali": "3", "Continent": "Europe", "WCTitles": "0"}, {"Land": "Tunisia", "Log_Population": "16.14", "Points": "701", "WCQuali": "5", "Continent": "Africa", "WCTitles": "0"}, {"Land": "USA", "Log_Population": "19.51", "Points": "847", "WCQuali": "10", "Continent": "Latin/North America", "WCTitles": "0"}, {"Land": "Ukraine", "Log_Population": "17.66", "Points": "761", "WCQuali": "1", "Continent": "Europe", "WCTitles": "0"}, {"Land": "Denmark", "Log_Population": "15.51", "Points": "657", "WCQuali": "5", "Continent": "Europe", "WCTitles": "0"}, {"Land": "Slovenia", "Log_Population": "14.51", "Points": "614", "WCQuali": "0", "Continent": "Europe", "WCTitles": "0"}, {"Land": "Czech Republic", "Log_Population": "16.14", "Points": "679", "WCQuali": "9", "Continent": "Europe", "WCTitles": "0"}, {"Land": "Montenegro", "Log_Population": "13.34", "Points": "560", "WCQuali": "0", "Continent": "Europe", "WCTitles": "0"}, {"Land": "Serbia", "Log_Population": "16.13", "Points": "671", "WCQuali": "12", "Continent": "Europe", "WCTitles": "0"}, {"Land": "Panama", "Log_Population": "15.02", "Points": "607", "WCQuali": "0", "Continent": "Latin/North America", "WCTitles": "0"}, {"Land": "Ghana", "Log_Population": "16.92", "Points": "682", "WCQuali": "3", "Continent": "Africa", "WCTitles": "0"}, {"Land": "Romania", "Log_Population": "16.92", "Points": "676", "WCQuali": "7", "Continent": "Europe", "WCTitles": "0"}, {"Land": "Faroe Islands", "Log_Population": "10.81", "Points": "431", "WCQuali": "0", "Continent": "Europe", "WCTitles": "0"}, {"Land": "Congo DR", "Log_Population": "17.95", "Points": "712", "WCQuali": "1", "Continent": "Africa", "WCTitles": "0"}, {"Land": "Korea Republic", "Log_Population": "17.70", "Points": "700", "WCQuali": "10", "Continent": "Asia", "WCTitles": "0"}, {"Land": "Australia", "Log_Population": "16.82", "Points": "661", "WCQuali": "5", "Continent": "Asia", "WCTitles": "0"}, {"Land": "Nigeria", "Log_Population": "18.70", "Points": "726", "WCQuali": "6", "Continent": "Africa", "WCTitles": "0"}, {"Land": "Bulgaria", "Log_Population": "15.82", "Points": "614", "WCQuali": "7", "Continent": "Europe", "WCTitles": "0"}, {"Land": "Scotland", "Log_Population": "15.44", "Points": "589", "WCQuali": "8", "Continent": "Europe", "WCTitles": "0"}, {"Land": "Saudi Arabia", "Log_Population": "17.11", "Points": "646", "WCQuali": "5", "Continent": "Asia", "WCTitles": "0"}, {"Land": "Japan", "Log_Population": "18.66", "Points": "685", "WCQuali": "6", "Continent": "Asia", "WCTitles": "0"}, {"Land": "Morocco", "Log_Population": "17.32", "Points": "633", "WCQuali": "5", "Continent": "Africa", "WCTitles": "0"}, {"Land": "Algeria", "Log_Population": "17.32", "Points": "628", "WCQuali": "4", "Continent": "Africa", "WCTitles": "0"}, {"Land": "Israel", "Log_Population": "15.66", "Points": "557", "WCQuali": "1", "Continent": "Asia", "WCTitles": "0"}, {"Land": "Armenia", "Log_Population": "14.90", "Points": "527", "WCQuali": "0", "Continent": "Europe", "WCTitles": "0"}, {"Land": "Albania", "Log_Population": "15.10", "Points": "533", "WCQuali": "0", "Continent": "Europe", "WCTitles": "0"}, {"Land": "Venezuela", "Log_Population": "17.14", "Points": "595", "WCQuali": "0", "Continent": "South America", "WCTitles": "0"}, {"Land": "Uzbekistan", "Log_Population": "17.12", "Points": "586", "WCQuali": "0", "Continent": "Asia", "WCTitles": "0"}, {"Land": "Haiti", "Log_Population": "15.93", "Points": "537", "WCQuali": "0", "Continent": "Latin/North America", "WCTitles": "0"}, {"Land": "Honduras", "Log_Population": "15.81", "Points": "524", "WCQuali": "3", "Continent": "Latin/North America", "WCTitles": "0"}, {"Land": "United Arab Emirates", "Log_Population": "14.15", "Points": "453", "WCQuali": "1", "Continent": "Asia", "WCTitles": "0"}, {"Land": "Cape Verde Islands", "Log_Population": "13.12", "Points": "418", "WCQuali": "0", "Continent": "Africa", "WCTitles": "0"}, {"Land": "Trinidad and Tobago", "Log_Population": "13.88", "Points": "439", "WCQuali": "1", "Continent": "Africa", "WCTitles": "0"}, {"Land": "Mali", "Log_Population": "16.28", "Points": "504", "WCQuali": "0", "Continent": "Africa", "WCTitles": "0"}, {"Land": "Jamaica", "Log_Population": "14.84", "Points": "458", "WCQuali": "1", "Continent": "Latin/North America", "WCTitles": "0"}, {"Land": "South Africa", "Log_Population": "17.67", "Points": "539", "WCQuali": "3", "Continent": "Africa", "WCTitles": "0"}, {"Land": "Russia", "Log_Population": "18.78", "Points": "561", "WCQuali": "11", "Continent": "Europe", "WCTitles": "0"}, {"Land": "Guinea", "Log_Population": "16.09", "Points": "474", "WCQuali": "0", "Continent": "Africa", "WCTitles": "0"}, {"Land": "Bolivia", "Log_Population": "16.03", "Points": "460", "WCQuali": "3", "Continent": "South America", "WCTitles": "0"}, {"Land": "Gabon", "Log_Population": "14.14", "Points": "392", "WCQuali": "0", "Continent": "Africa", "WCTitles": "0"}, {"Land": "Uganda", "Log_Population": "17.07", "Points": "463", "WCQuali": "0", "Continent": "Africa", "WCTitles": "0"}, {"Land": "Qatar", "Log_Population": "13.69", "Points": "369", "WCQuali": "0", "Continent": "Asia", "WCTitles": "0"}, {"Land": "Belarus", "Log_Population": "16.15", "Points": "428", "WCQuali": "1", "Continent": "Europe", "WCTitles": "0"}, {"Land": "Congo", "Log_Population": "14.90", "Points": "392", "WCQuali": "1", "Continent": "Africa", "WCTitles": "0"}, {"Land": "Syria", "Log_Population": "16.78", "Points": "426", "WCQuali": "0", "Continent": "Asia", "WCTitles": "0"}, {"Land": "Cyprus", "Log_Population": "13.58", "Points": "343", "WCQuali": "0", "Continent": "Europe", "WCTitles": "0"}, {"Land": "Norway", "Log_Population": "15.34", "Points": "387", "WCQuali": "3", "Continent": "Europe", "WCTitles": "0"}, {"Land": "Benin", "Log_Population": "15.95", "Points": "396", "WCQuali": "0", "Continent": "Africa", "WCTitles": "0"}, {"Land": "Kenya", "Log_Population": "17.45", "Points": "428", "WCQuali": "0", "Continent": "Africa", "WCTitles": "0"}, {"Land": "Estonia", "Log_Population": "14.10", "Points": "331", "WCQuali": "0", "Continent": "Europe", "WCTitles": "0"}, {"Land": "Libya", "Log_Population": "15.53", "Points": "361", "WCQuali": "0", "Continent": "Africa", "WCTitles": "0"}, {"Land": "Lithuania", "Log_Population": "15.09", "Points": "331", "WCQuali": "0", "Continent": "Europe", "WCTitles": "0"}, {"Land": "Equatorial Guinea", "Log_Population": "13.22", "Points": "287", "WCQuali": "0", "Continent": "South America", "WCTitles": "0"}, {"Land": "Finland", "Log_Population": "15.47", "Points": "335", "WCQuali": "0", "Continent": "Europe", "WCTitles": "0"}, {"Land": "Guatemala", "Log_Population": "16.36", "Points": "352", "WCQuali": "0", "Continent": "Latin/North America", "WCTitles": "0"}, {"Land": "Togo", "Log_Population": "15.53", "Points": "320", "WCQuali": "1", "Continent": "Africa", "WCTitles": "0"}, {"Land": "Zambia", "Log_Population": "16.26", "Points": "334", "WCQuali": "0", "Continent": "Africa", "WCTitles": "0"}, {"Land": "China PR", "Log_Population": "21.00", "Points": "425", "WCQuali": "1", "Continent": "Asia", "WCTitles": "0"}, {"Land": "Jordan", "Log_Population": "15.68", "Points": "311", "WCQuali": "0", "Continent": "Asia", "WCTitles": "0"}, {"Land": "New Zealand", "Log_Population": "15.23", "Points": "301", "WCQuali": "2", "Continent": "Asia", "WCTitles": "0"}, {"Land": "Oman", "Log_Population": "14.95", "Points": "290", "WCQuali": "0", "Continent": "Asia", "WCTitles": ""}, {"Land": "Mozambique", "Log_Population": "16.75", "Points": "323", "WCQuali": "0", "Continent": "Africa", "WCTitles": "0"}, {"Land": "Zimbabwe", "Log_Population": "16.33", "Points": "304", "WCQuali": "0", "Continent": "Africa", "WCTitles": "0"}, {"Land": "Latvia", "Log_Population": "14.63", "Points": "265", "WCQuali": "0", "Continent": "Europe", "WCTitles": "0"}]
